scenario/__init__.py
scenario/_consistency_checker.py
scenario/_ops_main_mock.py
scenario/_runtime.py
scenario/context.py
scenario/errors.py
scenario/logger.py
scenario/mocking.py
scenario/py.typed
scenario/state.py
ops_scenario-8.5.0.dist-info/METADATA
ops_scenario-8.5.0.dist-info/WHEEL
ops_scenario-8.5.0.dist-info/top_level.txt
ops_scenario-8.5.0.dist-info/RECORD
