Metadata-Version: 2.4
Name: ops-scenario
Version: 8.5.0
Summary: Python library providing a state-transition testing API for Operator Framework charms.
Author-email: Pietro Pasotti <pietro.pasotti@canonical.com>
Maintainer: The Charm Tech team at Canonical Ltd.
License-Expression: Apache-2.0
Project-URL: Homepage, https://github.com/canonical/operator
Project-URL: Bug Tracker, https://github.com/canonical/operator/issues
Keywords: juju,test
Classifier: Development Status :: 5 - Production/Stable
Classifier: Framework :: Pytest
Classifier: Intended Audience :: Developers
Classifier: Topic :: Software Development :: Quality Assurance
Classifier: Topic :: Software Development :: Testing
Classifier: Topic :: Utilities
Requires-Python: >=3.10
Requires-Dist: ops==3.5.0
Requires-Dist: PyYAML>=6.0.1
Requires-Dist: typing_extensions>=4.9.0
